README.txt
setup.py
payflowpro/__init__.py
payflowpro/classes.py
payflowpro/client.py
payflowpro/tests/__init__.py
payflowpro/tests/client.py
python_payflowpro.egg-info/PKG-INFO
python_payflowpro.egg-info/SOURCES.txt
python_payflowpro.egg-info/dependency_links.txt
python_payflowpro.egg-info/top_level.txt