Metadata-Version: 1.0
Name: python-payflowpro
Version: 0.2-final
Summary: PayPal PayFlowPro API client library
Home-page: http://code.google.com/p/python-payflowpro/
Author: John D'Agostino
Author-email: john.dagostino@gmail.com
License: UNKNOWN
Platform: UNKNOWN
Classifier: Development Status :: 4 - Beta
Classifier: Intended Audience :: Developers
Classifier: License :: OSI Approved :: Apache Software License
Classifier: Operating System :: OS Independent
Classifier: Programming Language :: Python
Classifier: Topic :: Software Development :: Libraries :: Python Modules
